pysarif/__init__.py
pysarif/_address.py
pysarif/_artifact.py
pysarif/_artifact_change.py
pysarif/_artifact_content.py
pysarif/_artifact_location.py
pysarif/_attachment.py
pysarif/_code_flow.py
pysarif/_configuration_override.py
pysarif/_conversion.py
pysarif/_edge.py
pysarif/_edge_traversal.py
pysarif/_exception.py
pysarif/_external_properties.py
pysarif/_external_property_file_reference.py
pysarif/_external_property_file_references.py
pysarif/_fix.py
pysarif/_graph.py
pysarif/_graph_traversal.py
pysarif/_invocation.py
pysarif/_loader.py
pysarif/_location.py
pysarif/_location_relationship.py
pysarif/_logical_location.py
pysarif/_message.py
pysarif/_multiformat_message_string.py
pysarif/_node.py
pysarif/_notification.py
pysarif/_physical_location.py
pysarif/_property_bag.py
pysarif/_rectangle.py
pysarif/_region.py
pysarif/_replacement.py
pysarif/_reporting_configuration.py
pysarif/_reporting_descriptor.py
pysarif/_reporting_descriptor_reference.py
pysarif/_reporting_descriptor_relationship.py
pysarif/_result.py
pysarif/_result_provenance.py
pysarif/_run.py
pysarif/_run_automation_details.py
pysarif/_sarif_log.py
pysarif/_special_locations.py
pysarif/_stack.py
pysarif/_stack_frame.py
pysarif/_suppression.py
pysarif/_thread_flow.py
pysarif/_thread_flow_location.py
pysarif/_tool.py
pysarif/_tool_component.py
pysarif/_tool_component_reference.py
pysarif/_translation_metadata.py
pysarif/_version_control_details.py
pysarif/_web_request.py
pysarif/_web_response.py
pysarif-0.1.0.dist-info/LICENSE
pysarif-0.1.0.dist-info/METADATA
pysarif-0.1.0.dist-info/WHEEL
pysarif-0.1.0.dist-info/top_level.txt
pysarif-0.1.0.dist-info/RECORD
