Metadata-Version: 2.1
Name: pysarif
Version: 0.1.0
Summary: Package to work with SARIF files as Python objects
Author-email: Kjeld Perquin <kjeld.perquin96@gmail.com>
License: MIT License
Project-URL: homepage, https://github.com/Kjeld-P/pysarif
Project-URL: documentation, https://github.com/Kjeld-P/pysarif/issues
Project-URL: repository, https://github.com/Kjeld-P/pysarif
Keywords: sarif,pysarif,package
Classifier: Development Status :: 4 - Beta
Classifier: Intended Audience :: Developers
Classifier: Topic :: Security
Classifier: Programming Language :: Python :: 3
Classifier: Programming Language :: Python :: 3 :: Only
Classifier: License :: OSI Approved :: MIT License
Classifier: Operating System :: OS Independent
Requires-Python: >=3.7
License-File: LICENSE
Requires-Dist: dataclasses-json
Provides-Extra: dev
